LICENSE
NOTICE
hmi_sim/__init__.py
hmi_sim/_version.py
hmi_sim/cli.py
hmi_sim/config.py
hmi_sim/core.py
hmi_sim/default_config.ini
hmi_sim/utils.py
hmi_sim-1.0.0.dist-info/METADATA
hmi_sim-1.0.0.dist-info/WHEEL
hmi_sim-1.0.0.dist-info/entry_points.txt
hmi_sim-1.0.0.dist-info/licenses/LICENSE
hmi_sim-1.0.0.dist-info/licenses/NOTICE
hmi_sim-1.0.0.dist-info/RECORD
