Metadata-Version: 2.4
Name: hmi-sim
Version: 1.0.0
Summary: A Python utility for simulating human-like mouse movement and task switching — useful for automation, UI testing, and system interaction simulations.
Project-URL: Homepage, https://rohitlal.in/pypi/hmi-sim
Project-URL: Repository, https://github.com/rohitlal125555/hmi-sim
Project-URL: Issues, https://github.com/rohitlal125555/hmi-sim/issues
Author-email: Rohit Lal <contact@rohitlal.in>
License: Apache License 2.0
License-File: LICENSE
License-File: NOTICE
Keywords: HMI,automation,input testing,keyboard,mouse,pyautogui,simulation,ui testing
Classifier: Development Status :: 5 - Production/Stable
Classifier: Intended Audience :: Developers
Classifier: Intended Audience :: Information Technology
Classifier: License :: OSI Approved :: Apache Software License
Classifier: Operating System :: Microsoft :: Windows
Classifier: Programming Language :: Python :: 3
Classifier: Programming Language :: Python :: 3.9
Classifier: Programming Language :: Python :: 3.10
Classifier: Programming Language :: Python :: 3.11
Classifier: Programming Language :: Python :: 3.12
Classifier: Topic :: Software Development :: Testing
Classifier: Topic :: Utilities
Requires-Python: >=3.9
Requires-Dist: pyautogui>=0.9.54
Requires-Dist: pywin32>=223
